atq/__init__.py
atq/__main__.py
atq/atqclient.py
atq/atqserver.py
atq/executor.py
atq-0.0.2.dist-info/DESCRIPTION.rst
atq-0.0.2.dist-info/METADATA
atq-0.0.2.dist-info/RECORD
atq-0.0.2.dist-info/WHEEL
atq-0.0.2.dist-info/entry_points.txt
atq-0.0.2.dist-info/metadata.json
atq-0.0.2.dist-info/top_level.txt
