Metadata-Version: 2.0
Name: atq
Version: 0.0.2
Summary: Async task queue for Python
Home-page: http://github.com/nvdv/atq
Author: nvdv
Author-email: aflatnine@gmail.com
License: BSD
Keywords: task queue,asyncio,async
Platform: UNKNOWN
Classifier: Development Status :: 3 - Alpha
Classifier: Environment :: Web Environment
Classifier: Intended Audience :: Developers
Classifier: Programming Language :: Python
Classifier: Programming Language :: Python :: 3
Classifier: Programming Language :: Python :: 3.5
Classifier: Topic :: Software Development
Requires-Python: >=3.5
Requires-Dist: cloudpickle (>=0.4)
